united_llm/__init__.py
united_llm/client.py
united_llm/py.typed
united_llm/providers/__init__.py
united_llm/providers/ollama.py
united_llm/providers/openrouter.py
united_llm/utils/__init__.py
united_llm/utils/image_input.py
united_llm/utils/logging.py
united_llm/utils/schema_parser.py
united_llm-0.1.6.dist-info/licenses/LICENSE
united_llm-0.1.6.dist-info/METADATA
united_llm-0.1.6.dist-info/WHEEL
united_llm-0.1.6.dist-info/entry_points.txt
united_llm-0.1.6.dist-info/top_level.txt
united_llm-0.1.6.dist-info/RECORD
