Metadata-Version: 2.4
Name: united-llm
Version: 0.1.6
Summary: A streamlined, lightweight LLM client library for OpenRouter and Ollama providers with structured output generation
Author-email: United LLM Team <contact@united-llm.com>
License-Expression: MIT
Project-URL: Homepage, https://github.com/xychenmsn/united-llm
Project-URL: Bug Reports, https://github.com/xychenmsn/united-llm/issues
Project-URL: Source, https://github.com/xychenmsn/united-llm
Project-URL: Documentation, https://github.com/xychenmsn/united-llm#readme
Keywords: llm,openai,ollama,openrouter,structured-output,pydantic,ai,vision,ocr,schema-validation
Classifier: Development Status :: 4 - Beta
Classifier: Intended Audience :: Developers
Classifier: Topic :: Scientific/Engineering :: Artificial Intelligence
Classifier: Programming Language :: Python :: 3
Classifier: Programming Language :: Python :: 3.8
Classifier: Programming Language :: Python :: 3.9
Classifier: Programming Language :: Python :: 3.10
Classifier: Programming Language :: Python :: 3.11
Classifier: Programming Language :: Python :: 3.12
Classifier: Operating System :: OS Independent
Requires-Python: >=3.8
License-File: LICENSE
Requires-Dist: instructor>=1.3.0
Requires-Dist: pydantic>=2.0.0
Requires-Dist: openai>=1.0.0
Requires-Dist: string-schema>=0.1.0
Requires-Dist: requests>=2.31.0
Requires-Dist: python-dotenv>=1.0.0
Requires-Dist: python-dateutil>=2.8.0
Provides-Extra: dev
Requires-Dist: pytest>=7.4.0; extra == "dev"
Requires-Dist: pytest-cov>=4.1.0; extra == "dev"
Requires-Dist: black>=23.0.0; extra == "dev"
Requires-Dist: flake8>=6.0.0; extra == "dev"
Requires-Dist: mypy>=1.5.0; extra == "dev"
Requires-Dist: pre-commit>=3.0.0; extra == "dev"
Provides-Extra: docs
Requires-Dist: mkdocs>=1.5.0; extra == "docs"
Requires-Dist: mkdocs-material>=9.0.0; extra == "docs"
Requires-Dist: mkdocstrings[python]>=0.22.0; extra == "docs"
Provides-Extra: all
Requires-Dist: pytest>=7.4.0; extra == "all"
Requires-Dist: pytest-cov>=4.1.0; extra == "all"
Requires-Dist: black>=23.0.0; extra == "all"
Requires-Dist: flake8>=6.0.0; extra == "all"
Requires-Dist: mypy>=1.5.0; extra == "all"
Requires-Dist: pre-commit>=3.0.0; extra == "all"
Requires-Dist: mkdocs>=1.5.0; extra == "all"
Requires-Dist: mkdocs-material>=9.0.0; extra == "all"
Requires-Dist: mkdocstrings[python]>=0.22.0; extra == "all"
Dynamic: license-file
